lemon_tools/__init__.py
lemon_tools/lib.py
lemon_tools-1.0.0.data/scripts/lemon-make-package
tests/__init__.py
tests/lib_test.py
lemon_tools-1.0.0.dist-info/METADATA
lemon_tools-1.0.0.dist-info/WHEEL
lemon_tools-1.0.0.dist-info/top_level.txt
lemon_tools-1.0.0.dist-info/RECORD
