Metadata-Version: 2.1
Name: lemon-tools
Version: 1.0.0
Summary: Module buider with CI included
Home-page: https://github.com/japandotorg/lemon-tools
Author: Lemon Rose
Author-email: yash.kul69@gmail.com
License: UNKNOWN
Platform: UNKNOWN
